nlpcloud/__init__.py
nlpcloud-1.1.46.dist-info/LICENSE
nlpcloud-1.1.46.dist-info/METADATA
nlpcloud-1.1.46.dist-info/WHEEL
nlpcloud-1.1.46.dist-info/top_level.txt
nlpcloud-1.1.46.dist-info/RECORD
