Metadata-Version: 2.1
Name: nlpcloud
Version: 1.1.46
Summary: Python client for the NLP Cloud API
Home-page: https://github.com/nlpcloud/nlpcloud-python
Author: Julien Salinas
Author-email: all@juliensalinas.com
License: MIT
Keywords: api,NLP,ai,deep learning,machine learning,data science,nlpcloud
License-File: LICENSE
Requires-Dist: requests
